ChildrenND.py
Evaluation.py
Extent.py
Hashmap.py
MC.py
N_1.py
PreprocessingND.py
Ruleset_based_JS.py
Ruleset_based_SC.py
Split.py
Tree.py
displayResult.py
makePredictions.py
produceClassifiers.py
MCTSRLV1/ChildrenND.py
MCTSRLV1/Evaluation.py
MCTSRLV1/Extent.py
MCTSRLV1/Hashmap.py
MCTSRLV1/MC.py
MCTSRLV1/N_1.py
MCTSRLV1/PreprocessingND.py
MCTSRLV1/Ruleset_based_JS.py
MCTSRLV1/Ruleset_based_SC.py
MCTSRLV1/SC_Classifier.py
MCTSRLV1/Split.py
MCTSRLV1/Tree.py
MCTSRLV1/__init__.py
MCTSRLV1/displayResult.py
MCTSRLV1/makePredictions.py
MCTSRLV1/produceClassifiers.py
MCTSRLV2/ChildrenND.py
MCTSRLV2/Evaluation.py
MCTSRLV2/Extent.py
MCTSRLV2/Hashmap.py
MCTSRLV2/MC.py
MCTSRLV2/N_1.py
MCTSRLV2/PreprocessingND.py
MCTSRLV2/Ruleset_based_JS.py
MCTSRLV2/Ruleset_based_SC.py
MCTSRLV2/SC_Classifier.py
MCTSRLV2/Split.py
MCTSRLV2/Tree.py
MCTSRLV2/__init__.py
MCTSRLV2/displayResult.py
MCTSRLV2/makePredictions.py
MCTSRLV2/produceClassifiers.py
MCTSRLV2-0.8.dist-info/LICENCE.txt
MCTSRLV2-0.8.dist-info/METADATA
MCTSRLV2-0.8.dist-info/WHEEL
MCTSRLV2-0.8.dist-info/top_level.txt
MCTSRLV2-0.8.dist-info/RECORD
